mdata_flow/__init__.py
mdata_flow/config.py
mdata_flow/datasets_manager/__init__.py
mdata_flow/datasets_manager/composites.py
mdata_flow/datasets_manager/context.py
mdata_flow/datasets_manager/downloader.py
mdata_flow/datasets_manager/interfaces.py
mdata_flow/datasets_manager/manager.py
mdata_flow/datasets_manager/utils.py
mdata_flow/datasets_manager/visitors/__init__.py
mdata_flow/datasets_manager/visitors/cache_mover_visitor.py
mdata_flow/datasets_manager/visitors/csv_saver_visitor.py
mdata_flow/datasets_manager/visitors/dataset_uploader_mlflow_visitor.py
mdata_flow/datasets_manager/visitors/figure_visitor.py
mdata_flow/datasets_manager/visitors/nested_visitor.py
mdata_flow/datasets_manager/visitors/preview_uploader_visitor.py
mdata_flow/datasets_manager/visitors/scoped_abs_info_uploader.py
mdata_flow/datasets_manager/visitors/typed_abs_visitor.py
mdata_flow/datasets_manager/visitors/utils.py
mdata_flow/datasets_manager/visitors/xxh_digest_visitor.py
mdata_flow/evidently_ext/__init__.py
mdata_flow/evidently_ext/column_count_by_category.py
mdata_flow/evidently_ext/visitors/count_by_category_report.py
mdata_flow/evidently_ext/visitors/data_quality_report.py
mdata_flow/evidently_ext/visitors/evidently_abs_report_visitor.py
mdata_flow/file_name_validator.py
mdata_flow/lazy_loader.py
mdata_flow/plotly_ext/__init__.py
mdata_flow/plotly_ext/func_library.py
mdata_flow/plotly_ext/visitors/plotly_boxplot_visitor.py
mdata_flow/plotly_ext/visitors/plotly_corr_visitor.py
mdata_flow/plotly_ext/visitors/plotly_density_visitor.py
mdata_flow/types.py
mdata_flow-0.0.9.dist-info/METADATA
mdata_flow-0.0.9.dist-info/WHEEL
mdata_flow-0.0.9.dist-info/RECORD
