Metadata-Version: 2.3
Name: mdata-flow
Version: 0.0.9
Summary: 
Author: Ilia Novikov
Author-email: nov.ilucha@yandex.ru
Requires-Python: >=3.11,<3.13
Classifier: Programming Language :: Python :: 3
Classifier: Programming Language :: Python :: 3.11
Classifier: Programming Language :: Python :: 3.12
Provides-Extra: compress
Provides-Extra: graphics
Provides-Extra: reports
Requires-Dist: evidently (>=0.6.5,<0.7.0) ; extra == "reports"
Requires-Dist: matplotlib (>=3.10.1,<4.0.0) ; extra == "graphics"
Requires-Dist: mlflow-skinny[databricks] (>=2.22.0,<2.23.0)
Requires-Dist: pandas (>=2.2.3,<3.0.0)
Requires-Dist: plotly (>=5.10.0,<6) ; extra == "graphics"
Requires-Dist: plotly (>=5.10.0,<6) ; extra == "reports"
Requires-Dist: pydantic (>=2.10.6,<3.0.0)
Requires-Dist: pydantic-settings (>=2.8.1,<3.0.0)
Requires-Dist: scipy (>=1.15.3,<2.0.0)
Requires-Dist: seaborn (>=0.13.2,<0.14.0) ; extra == "graphics"
Requires-Dist: xxhash (>=3.5.0,<4.0.0)
Requires-Dist: zstandard (>=0.23.0,<0.24.0) ; extra == "compress"
